<?xml version="1.0" encoding="UTF-8"?><record_update table="announcement">
    <announcement action="INSERT_OR_UPDATE">
        <active>true</active>
        <click_target/>
        <details/>
        <details_link_text/>
        <details_page/>
        <details_url/>
        <dismiss_options>dismissible</dismiss_options>
        <display_first>false</display_first>
        <display_style display_value="Normal">704dedd6e7d4030075c2a117c2f6a91b</display_style>
        <from>2022-08-31 11:00:00</from>
        <glyph>info-circle</glyph>
        <glyph_alt_text/>
        <name>New Service Provider</name>
        <public>true</public>
        <roles/>
        <show_for_unauthenticated_users_only>false</show_for_unauthenticated_users_only>
        <summary>A new Service Provider will be announced for this service in 2023. &#13;
&#13;
The successful provider will take over service commencing the 6th April 2024</summary>
        <sys_class_name>announcement</sys_class_name>
        <sys_created_by>des.king.ems</sys_created_by>
        <sys_created_on>2022-08-31 15:55:36</sys_created_on>
        <sys_id>f49ead971b29d5906eb0a6c0604bcb1e</sys_id>
        <sys_mod_count>0</sys_mod_count>
        <sys_name>New Service Provider</sys_name>
        <sys_package display_value="Electronic Monitoring" source="x_ster2_emfs">55b3012a1b8595106eb0a6c0604bcb35</sys_package>
        <sys_policy/>
        <sys_scope display_value="Electronic Monitoring">55b3012a1b8595106eb0a6c0604bcb35</sys_scope>
        <sys_update_name>announcement_f49ead971b29d5906eb0a6c0604bcb1e</sys_update_name>
        <sys_updated_by>des.king.ems</sys_updated_by>
        <sys_updated_on>2022-08-31 15:55:36</sys_updated_on>
        <title>New Service Provider</title>
        <to>2024-12-31 23:59:59</to>
        <type>67eaf134e7a3320075c2a117c2f6a9d2,52fa79f8e763320075c2a117c2f6a991</type>
    </announcement>
    <sys_translated_text action="delete_multiple" query="documentkey=f49ead971b29d5906eb0a6c0604bcb1e"/>
</record_update>
