<?xml version="1.0" encoding="UTF-8"?><record_update table="item_option_new">
    <item_option_new action="DELETE">
        <active>true</active>
        <attributes/>
        <cat_item display_value="New Order">4a32331e87471910952f87f5cebb35c6</cat_item>
        <category/>
        <choice_direction>across</choice_direction>
        <choice_field/>
        <choice_table/>
        <create_roles/>
        <default_html_value/>
        <default_value/>
        <delete_roles/>
        <delivery_plan/>
        <description/>
        <display_title>false</display_title>
        <do_not_select_first>true</do_not_select_first>
        <dynamic_default_value/>
        <dynamic_ref_qual/>
        <enable_also_request_for>false</enable_also_request_for>
        <example_text/>
        <field>exclusion_address_radius</field>
        <global>false</global>
        <help_tag>More information</help_tag>
        <help_text/>
        <hidden>false</hidden>
        <include_none>false</include_none>
        <instructions/>
        <layout>normal</layout>
        <list_table/>
        <lookup_label/>
        <lookup_price/>
        <lookup_table/>
        <lookup_unique>false</lookup_unique>
        <lookup_value/>
        <macro/>
        <macroponent/>
        <mandatory>false</mandatory>
        <map_to_field>true</map_to_field>
        <mask_use_confirmation>false</mask_use_confirmation>
        <mask_use_encryption>false</mask_use_encryption>
        <name>radius</name>
        <order>3300</order>
        <price_if_checked>0</price_if_checked>
        <pricing_implications>false</pricing_implications>
        <published_ref display_value="Radius">8bd4905a1b8b95106eb0a6c0604bcb6e</published_ref>
        <question_text>Radius</question_text>
        <read_only>false</read_only>
        <read_roles/>
        <read_script/>
        <rec_lookup_price/>
        <rec_price_if_checked>0</rec_price_if_checked>
        <record/>
        <record_producer_table>x_ster2_emfs_monitoring_order</record_producer_table>
        <reference/>
        <reference_qual>undefined</reference_qual>
        <reference_qual_condition>undefined</reference_qual_condition>
        <rich_text/>
        <roles_to_use_also_request_for/>
        <save_script/>
        <scale_max>5</scale_max>
        <scale_min>0</scale_min>
        <show_help>false</show_help>
        <show_help_on_load>false</show_help_on_load>
        <sp_widget/>
        <summary_macro/>
        <sys_class_name>item_option_new</sys_class_name>
        <sys_created_by>hasnaat.khan.ems</sys_created_by>
        <sys_created_on>2022-11-11 12:27:15</sys_created_on>
        <sys_id>4f32771e87471910952f87f5cebb3548</sys_id>
        <sys_mod_count>5</sys_mod_count>
        <sys_name>Radius</sys_name>
        <sys_package display_value="Electronic Monitoring" source="x_ster2_emfs">55b3012a1b8595106eb0a6c0604bcb35</sys_package>
        <sys_policy/>
        <sys_scope display_value="Electronic Monitoring">55b3012a1b8595106eb0a6c0604bcb35</sys_scope>
        <sys_update_name>item_option_new_4f32771e87471910952f87f5cebb3548</sys_update_name>
        <sys_updated_by>hasnaat.khan.ems</sys_updated_by>
        <sys_updated_on>2022-11-11 12:31:24</sys_updated_on>
        <table/>
        <tooltip/>
        <type>3</type>
        <ui_page/>
        <unique>false</unique>
        <use_dynamic_default>false</use_dynamic_default>
        <use_reference_qualifier>simple</use_reference_qualifier>
        <validate_regex/>
        <variable_name/>
        <variable_set/>
        <variable_width/>
        <visibility>1</visibility>
        <visible_bundle>true</visible_bundle>
        <visible_guide>true</visible_guide>
        <visible_standalone>true</visible_standalone>
        <visible_summary>true</visible_summary>
        <write_roles/>
    </item_option_new>
    <sys_translated_text action="DELETE" query="documentkey=4f32771e87471910952f87f5cebb3548"/>
    <fx_price action="DELETE" query="id=4f32771e87471910952f87f5cebb3548"/>
    <fx_price action="DELETE">
        <amount>0</amount>
        <currency display_value="GBP">GBP</currency>
        <field>price_if_checked</field>
        <id>4f32771e87471910952f87f5cebb3548</id>
        <parent/>
        <reference_amount>0</reference_amount>
        <reference_currency display_value="USD">USD</reference_currency>
        <sys_created_by>hasnaat.khan.ems</sys_created_by>
        <sys_created_on>2022-11-11 12:27:15</sys_created_on>
        <sys_id>0332771e87471910952f87f5cebb354c</sys_id>
        <sys_mod_count>0</sys_mod_count>
        <sys_updated_by>hasnaat.khan.ems</sys_updated_by>
        <sys_updated_on>2022-11-11 12:27:15</sys_updated_on>
        <table>item_option_new</table>
        <type>calculated</type>
    </fx_price>
    <fx_price action="DELETE">
        <amount>0</amount>
        <currency display_value="GBP">GBP</currency>
        <field>rec_price_if_checked</field>
        <id>4f32771e87471910952f87f5cebb3548</id>
        <parent/>
        <reference_amount>0</reference_amount>
        <reference_currency display_value="USD">USD</reference_currency>
        <sys_created_by>hasnaat.khan.ems</sys_created_by>
        <sys_created_on>2022-11-11 12:27:15</sys_created_on>
        <sys_id>c332771e87471910952f87f5cebb354b</sys_id>
        <sys_mod_count>0</sys_mod_count>
        <sys_updated_by>hasnaat.khan.ems</sys_updated_by>
        <sys_updated_on>2022-11-11 12:27:15</sys_updated_on>
        <table>item_option_new</table>
        <type>calculated</type>
    </fx_price>
    <sys_update_version action="INSERT_OR_UPDATE">
        <action>DELETE</action>
        <application display_value="Electronic Monitoring">55b3012a1b8595106eb0a6c0604bcb35</application>
        <file_path/>
        <instance_id>f4948f24dbc9599449eac5970596198f</instance_id>
        <instance_name>soprasteriafieldservicespov</instance_name>
        <name>item_option_new_4f32771e87471910952f87f5cebb3548</name>
        <payload><![CDATA[<?xml version="1.0" encoding="UTF-8"?><record_update table="item_option_new"><item_option_new action="INSERT_OR_UPDATE"><active>true</active><attributes/><cat_item display_value="New Order">4a32331e87471910952f87f5cebb35c6</cat_item><category/><choice_direction>across</choice_direction><choice_field/><choice_table/><create_roles/><default_html_value/><default_value/><delete_roles/><delivery_plan/><description/><display_title>false</display_title><do_not_select_first>true</do_not_select_first><dynamic_default_value/><dynamic_ref_qual/><enable_also_request_for>false</enable_also_request_for><example_text/><field>exclusion_address_radius</field><global>false</global><help_tag>More information</help_tag><help_text/><hidden>false</hidden><include_none>false</include_none><instructions/><layout>normal</layout><list_table/><lookup_label/><lookup_price/><lookup_table/><lookup_unique>false</lookup_unique><lookup_value/><macro/><macroponent/><mandatory>false</mandatory><map_to_field>true</map_to_field><mask_use_confirmation>false</mask_use_confirmation><mask_use_encryption>false</mask_use_encryption><name>radius</name><order>3300</order><price_if_checked>0</price_if_checked><pricing_implications>false</pricing_implications><published_ref display_value="Radius">8bd4905a1b8b95106eb0a6c0604bcb6e</published_ref><question_text>Radius</question_text><read_only>false</read_only><read_roles/><read_script/><rec_lookup_price/><rec_price_if_checked>0</rec_price_if_checked><record/><record_producer_table>x_ster2_emfs_monitoring_order</record_producer_table><reference/><reference_qual>undefined</reference_qual><reference_qual_condition>undefined</reference_qual_condition><rich_text/><roles_to_use_also_request_for/><save_script/><scale_max>5</scale_max><scale_min>0</scale_min><show_help>false</show_help><show_help_on_load>false</show_help_on_load><sp_widget/><summary_macro/><sys_class_name>item_option_new</sys_class_name><sys_created_by>hasnaat.khan.ems</sys_created_by><sys_created_on>2022-11-11 12:27:15</sys_created_on><sys_id>4f32771e87471910952f87f5cebb3548</sys_id><sys_mod_count>5</sys_mod_count><sys_name>Radius</sys_name><sys_package display_value="Electronic Monitoring" source="x_ster2_emfs">55b3012a1b8595106eb0a6c0604bcb35</sys_package><sys_policy/><sys_scope display_value="Electronic Monitoring">55b3012a1b8595106eb0a6c0604bcb35</sys_scope><sys_update_name>item_option_new_4f32771e87471910952f87f5cebb3548</sys_update_name><sys_updated_by>hasnaat.khan.ems</sys_updated_by><sys_updated_on>2022-11-11 12:31:24</sys_updated_on><table/><tooltip/><type>3</type><ui_page/><unique>false</unique><use_dynamic_default>false</use_dynamic_default><use_reference_qualifier>simple</use_reference_qualifier><validate_regex/><variable_name/><variable_set/><variable_width/><visibility>1</visibility><visible_bundle>true</visible_bundle><visible_guide>true</visible_guide><visible_standalone>true</visible_standalone><visible_summary>true</visible_summary><write_roles/></item_option_new><sys_translated_text action="delete_multiple" query="documentkey=4f32771e87471910952f87f5cebb3548"/><fx_price action="delete_multiple" query="id=4f32771e87471910952f87f5cebb3548"/><fx_price action="INSERT_OR_UPDATE"><amount>0</amount><currency display_value="GBP">GBP</currency><field>price_if_checked</field><id>4f32771e87471910952f87f5cebb3548</id><parent/><reference_amount>0</reference_amount><reference_currency display_value="USD">USD</reference_currency><sys_created_by>hasnaat.khan.ems</sys_created_by><sys_created_on>2022-11-11 12:27:15</sys_created_on><sys_id>0332771e87471910952f87f5cebb354c</sys_id><sys_mod_count>0</sys_mod_count><sys_updated_by>hasnaat.khan.ems</sys_updated_by><sys_updated_on>2022-11-11 12:27:15</sys_updated_on><table>item_option_new</table><type>calculated</type></fx_price><fx_price action="INSERT_OR_UPDATE"><amount>0</amount><currency display_value="GBP">GBP</currency><field>rec_price_if_checked</field><id>4f32771e87471910952f87f5cebb3548</id><parent/><reference_amount>0</reference_amount><reference_currency display_value="USD">USD</reference_currency><sys_created_by>hasnaat.khan.ems</sys_created_by><sys_created_on>2022-11-11 12:27:15</sys_created_on><sys_id>c332771e87471910952f87f5cebb354b</sys_id><sys_mod_count>0</sys_mod_count><sys_updated_by>hasnaat.khan.ems</sys_updated_by><sys_updated_on>2022-11-11 12:27:15</sys_updated_on><table>item_option_new</table><type>calculated</type></fx_price></record_update>]]></payload>
        <payload_hash>1456382382</payload_hash>
        <record_name>Radius</record_name>
        <reverted_from/>
        <source>877c8dab877e1950952f87f5cebb356c</source>
        <source_table>sys_update_set</source_table>
        <state>current</state>
        <sys_created_by>hasnaat.khan.ems</sys_created_by>
        <sys_created_on>2022-11-11 12:31:24</sys_created_on>
        <sys_id>7b23779e87471910952f87f5cebb35c6</sys_id>
        <sys_mod_count>0</sys_mod_count>
        <sys_recorded_at>18466ac64d70000001</sys_recorded_at>
        <sys_updated_by>hasnaat.khan.ems</sys_updated_by>
        <sys_updated_on>2022-11-11 12:31:24</sys_updated_on>
        <type>Variable</type>
        <update_guid>bf23779e174719100c0350501e4be2c5</update_guid>
        <update_guid_history>bf23779e174719100c0350501e4be2c5:1456382382,9913739e0f47191085be03334834567f:847229135,fff2bf5e174719106f1d9d5701c4a31c:238075888,a7c23b5ebd4719108d78d4dba1e3e339:-371077359,b8b2f35e2f4719102057197dabc816bd:-887546905,c332771ef6471910e1bd7fbfa2a1cc55:-2105853399</update_guid_history>
    </sys_update_version>
    <sys_metadata_delete action="INSERT_OR_UPDATE">
        <sys_audit_delete display_value="Radius">924333de87471910952f87f5cebb35e0</sys_audit_delete>
        <sys_class_name>sys_metadata_delete</sys_class_name>
        <sys_created_by>system</sys_created_by>
        <sys_created_on>2022-11-11 12:31:51</sys_created_on>
        <sys_db_object display_value="" name="item_option_new">item_option_new</sys_db_object>
        <sys_id>2a8f5e3fbb1748689d41250ba56b5d04</sys_id>
        <sys_metadata>4f32771e87471910952f87f5cebb3548</sys_metadata>
        <sys_mod_count>0</sys_mod_count>
        <sys_name>Radius</sys_name>
        <sys_package display_value="Electronic Monitoring" source="x_ster2_emfs">55b3012a1b8595106eb0a6c0604bcb35</sys_package>
        <sys_parent display_value="">4a32331e87471910952f87f5cebb35c6</sys_parent>
        <sys_policy/>
        <sys_scope display_value="Electronic Monitoring">55b3012a1b8595106eb0a6c0604bcb35</sys_scope>
        <sys_scope_delete display_value="">1728f35f3cdf4e24be031eef5c348910</sys_scope_delete>
        <sys_update_name>item_option_new_4f32771e87471910952f87f5cebb3548</sys_update_name>
        <sys_update_version display_value="item_option_new_4f32771e87471910952f87f5cebb3548">7b23779e87471910952f87f5cebb35c6</sys_update_version>
        <sys_updated_by>system</sys_updated_by>
        <sys_updated_on>2022-11-11 12:31:51</sys_updated_on>
    </sys_metadata_delete>
</record_update>
